{
  "srcFiles": [
    "./projects/canopy/src/assets/brand-icons/**/*.svg"
  ],
  "outputDirectory": "./projects/canopy/src/lib/brand-icons-files",
  "iconsFolderName": "set",
  "typeName": "BrandIconName",
  "prefix": "lgBrandIcon",
  "optimizeForLazyLoading": true,
  "modelFileName": "brand-icons-files.interface",
  "additionalModelOutputPath": "projects/canopy/src/lib/brand-icon",
  "interfaceName": "BrandIcon",
  "exportCompleteIconSet": true,
  "completeIconSetName": "lgBrandIconsArray",
  "delimiter": "KEBAB",
  "svgoConfig": {
    "plugins": [
      {
        "name": "preset-default",
        "params": {
          "overrides": {
            "cleanupIds": false
          }
        }
      },
      "removeDimensions"
    ]
  }
}
